MANIFEST.in
account_bank_statement_report.xml
account_bank_statement_view.xml
setup.py
./__init__.py
./__openerp__.py
./account_bank_statement.py
./res_partner_bank.py
./report/__init__.py
./report/bank_statement_balance_report.py
./wizard/__init__.py
./wizard/cancel_statement_line.py
./wizard/confirm_statement_line.py
data/account_bank_statement_extensions_data.xml
i18n/account_bank_statement_extensions.pot
i18n/ar.po
i18n/bs.po
i18n/cs.po
i18n/da.po
i18n/de.po
i18n/en_GB.po
i18n/es.po
i18n/es_CR.po
i18n/es_EC.po
i18n/es_MX.po
i18n/fi.po
i18n/fr.po
i18n/gu.po
i18n/hr.po
i18n/hu.po
i18n/it.po
i18n/ja.po
i18n/mk.po
i18n/mn.po
i18n/nb.po
i18n/nl.po
i18n/pl.po
i18n/pt.po
i18n/pt_BR.po
i18n/ro.po
i18n/ru.po
i18n/sl.po
i18n/sr@latin.po
i18n/sv.po
i18n/tr.po
i18n/zh_CN.po
i18n/zh_TW.po
openerp_account_bank_statement_extensions.egg-info/PKG-INFO
openerp_account_bank_statement_extensions.egg-info/SOURCES.txt
openerp_account_bank_statement_extensions.egg-info/dependency_links.txt
openerp_account_bank_statement_extensions.egg-info/requires.txt
openerp_account_bank_statement_extensions.egg-info/top_level.txt
report/bank_statement_balance_report.rml
security/ir.model.access.csv
wizard/cancel_statement_line_wizard.xml
wizard/confirm_statement_line_wizard.xml